libbam
