Metadata-Version: 1.1
Name: libbam
Version: 0.2.0
Summary: A library for reading and writing SAM/BAM files.
Home-page: https://github.com/antonybholmes/libbam
Author: Antony B Holmes
Author-email: antony.b.holmes@gmail.com
License: UNKNOWN
Platform: UNKNOWN
Classifier: Programming Language :: Python :: 3
Classifier: License :: OSI Approved :: MIT License
Classifier: Operating System :: OS Independent
